{
  "schema_version": 1,
  "generated_at": "2026-07-14T12:04:12.374623Z",
  "sources": [
    {
      "source_id": "mit-ssac-research-paper-competition",
      "status": "ok",
      "checked_at": "2026-07-14T12:04:12.374623Z",
      "url": "https://www.sloansportsconference.com/research-paper-competition",
      "final_url": "https://www.sloansportsconference.com/research-paper-competition",
      "http_status": 200,
      "content_sha256": "2876d7c7c7f9d9fcb34da9697914f6676fe9f415be7a2de4c563df8aa1b0bdd1",
      "changed": false,
      "missing_markers": [],
      "date_mentions": [
        "7 are now open! Submit your abstract here . Abstract submissions due: Oct. 1, 2026 11:59 p.m. EST ‍ Abstracts are selected based on the novelty, academi",
        "sent out: Late-October 2026 Full paper submission due (if selected): Dec. 4, 2026 11:59 p.m. Finalists and posters announced: Late-January 2027 Submiss"
      ],
      "error": ""
    },
    {
      "source_id": "mit-ssac-competitions",
      "status": "ok",
      "checked_at": "2026-07-14T12:04:12.374623Z",
      "url": "https://www.sloansportsconference.com/competitions",
      "final_url": "https://www.sloansportsconference.com/competitions",
      "http_status": 200,
      "content_sha256": "f398eb0d49b9abff1f15aaa33aeb1fbd3d7d6591beab81ad03839953be28e8ff",
      "changed": false,
      "missing_markers": [],
      "date_mentions": [],
      "error": ""
    },
    {
      "source_id": "nessis",
      "status": "error",
      "checked_at": "2026-07-14T12:04:12.374623Z",
      "url": "https://www.nessis.org/call.html",
      "final_url": "",
      "http_status": null,
      "content_sha256": "",
      "changed": false,
      "missing_markers": [],
      "date_mentions": [],
      "error": "<urlopen error [SSL: CERTIFICATE_VERIFY_FAILED] certificate verify failed: Hostname mismatch, certificate is not valid for 'www.nessis.org'. (_ssl.c:1010)>"
    },
    {
      "source_id": "cassis",
      "status": "ok",
      "checked_at": "2026-07-14T12:04:12.374623Z",
      "url": "https://www.cascadiasports.com/",
      "final_url": "https://www.cascadiasports.com/",
      "http_status": 200,
      "content_sha256": "8a067706037e9fc7978b32604e186b0cbb98c9a72cb610da28a1d501e697a782",
      "changed": true,
      "missing_markers": [],
      "date_mentions": [
        "cal Information CASSIS The Cascadia Symposium on Statistics in Sports September 12, 2026 Vancouver, Canada About CASSIS The 2026 Cascadia Symposium on Statist"
      ],
      "error": ""
    },
    {
      "source_id": "cmsac",
      "status": "ok",
      "checked_at": "2026-07-14T12:04:12.374623Z",
      "url": "https://www.cmsaconference.com/",
      "final_url": "https://www.cmsaconference.com/",
      "http_status": 200,
      "content_sha256": "28bc79a4b68096bcedce7ebe39a529ee711242427eb371dbba33873aa11240ea",
      "changed": false,
      "missing_markers": [],
      "date_mentions": [],
      "error": ""
    },
    {
      "source_id": "csas",
      "status": "ok",
      "checked_at": "2026-07-14T12:04:12.374623Z",
      "url": "https://statds.org/events/csas2026/",
      "final_url": "https://statds.org/events/csas2026/",
      "http_status": 200,
      "content_sha256": "850f8749d6a6a89718a0dc30d52d800177cbc89a0050c3460b2784ea1d069813",
      "changed": false,
      "missing_markers": [],
      "date_mentions": [],
      "error": ""
    },
    {
      "source_id": "mlsa",
      "status": "ok",
      "checked_at": "2026-07-14T12:04:12.374623Z",
      "url": "https://dtai.cs.kuleuven.be/events/MLSA26/",
      "final_url": "https://dtai.cs.kuleuven.be/events/MLSA26/",
      "http_status": 200,
      "content_sha256": "92ebd8ff753cbe1f6bd25a4b0268410ebfece2c7ee52b380f8e7c5ba977d34fe",
      "changed": false,
      "missing_markers": [],
      "date_mentions": [
        "n Machine Learning and Data Mining for Sports Analytics Naples, Italy Sep 7, 2026 Call for Papers Submission Key Dates Schedule Organisers Previous Edi",
        "located with ECML/PKDD 2026 . It will take place in Naples, Italy on September 7, 2026 . The workshop program will feature invited talks from leading resear",
        "erformance prediction. View the full CfP → Key Dates Paper Submission June 5, 2026 Workshop Date September 7, 2026 Full schedule → Proceedings As in pre"
      ],
      "error": ""
    },
    {
      "source_id": "mathsport-international",
      "status": "ok",
      "checked_at": "2026-07-14T12:04:12.374623Z",
      "url": "https://www.mathsportinternational.com/",
      "final_url": "https://www.mathsportinternational.com/",
      "http_status": 200,
      "content_sha256": "e1eb2d4f8e34158cff2bf62d09a70bd8d5857091368c4d3f38390578d96a3ff0",
      "changed": false,
      "missing_markers": [],
      "date_mentions": [],
      "error": ""
    },
    {
      "source_id": "mathsport-asia",
      "status": "ok",
      "checked_at": "2026-07-14T12:04:12.374623Z",
      "url": "https://iimk.ac.in/apps/mathsport26/",
      "final_url": "https://iimk.ac.in/apps/mathsport26/",
      "http_status": 200,
      "content_sha256": "798fb95f219b0af64b97a2fdde76da0714ba5afae2986b40f692fab77cbc25a7",
      "changed": false,
      "missing_markers": [],
      "date_mentions": [
        "hould be written in English. The deadline for submitting abstracts is August 3, 2026 . Acceptance of abstract will be notified by August 18, 2026 Submit A",
        "tracts is August 3, 2026 . Acceptance of abstract will be notified by August 18, 2026 Submit Abstract Abstracts must be submitted through the Microsoft CMT",
        "stract Submission Begins March 16 , 2026 Abstract Submission Deadline August 03, 2026 Intimation of Decision August 18, 2026 Registration Begins August 18",
        "t 03, 2026 Intimation of Decision August 18, 2026 Registration Begins August 18, 2025 Early Registration Deadline September 30, 2026 Last Registration Dead",
        "2026 Registration Begins August 18, 2025 Early Registration Deadline September 30, 2026 Last Registration Deadline With Higher Fee November 2, 2026 Last Date",
        "eadline September 30, 2026 Last Registration Deadline With Higher Fee November 2, 2026 Last Date to Submit the Complete Paper February, 28 2027 Plenary Spea"
      ],
      "error": ""
    },
    {
      "source_id": "hudl-performance-insights",
      "status": "ok",
      "checked_at": "2026-07-14T12:04:12.374623Z",
      "url": "https://www.hudl.com/blog/hpi-2026-research-competition",
      "final_url": "https://www.hudl.com/blog/hpi-2026-research-competition",
      "http_status": 200,
      "content_sha256": "40617e43c1054e2fb580917167546facb4fa43d0d4cc6ec077dbe2f8b54287f4",
      "changed": false,
      "missing_markers": [],
      "date_mentions": [
        "pany News Hudl Performance Insights 2026: Call For Research Proposals 10 Jun 2026 3 min Read Hudl open submissions for the Hudl Performance Insights 20",
        "submit a proposal, please complete the application process by Friday 3rd July 2026. Your proposal should clearly outline your hypothesis, the specific d",
        "ies How Columbia Women's Basketball Built a Culture of Accountability 7 Jul 2026 Hudl and Football Federation Northern Territory Announce Exclusive Mu",
        "ern Territory Announce Exclusive Multi-Year Scouting Rights Agreement 6 Jul 2026 Hudl Lens: Building Human Advantage in an AI World 26 Jun 2026 2026 S",
        "reement 6 Jul 2026 Hudl Lens: Building Human Advantage in an AI World 26 Jun 2026 2026 Sudamericano U17: South America’s New Wave of Stars 23 Jun 2026",
        "26 Jun 2026 2026 Sudamericano U17: South America’s New Wave of Stars 23 Jun 2026 The Illinois Project: Building an Analytical Powerhouse 5 Jun 2026 Hu",
        "s 23 Jun 2026 The Illinois Project: Building an Analytical Powerhouse 5 Jun 2026 Hudl and the Canadian Hockey League Renew Multi-Season Scouting Right",
        "e Canadian Hockey League Renew Multi-Season Scouting Rights Agreement 4 Jun 2026 Solutions High School Club Collegiate Division I Colleges Fan Engagem"
      ],
      "error": ""
    },
    {
      "source_id": "nfl-big-data-bowl",
      "status": "ok",
      "checked_at": "2026-07-14T12:04:12.374623Z",
      "url": "https://operations.nfl.com/programs-initiatives/innovation/big-data-bowl",
      "final_url": "https://operations.nfl.com/programs-initiatives/innovation/big-data-bowl",
      "http_status": 200,
      "content_sha256": "50048a4dc2195112354fa97608d8bf2f400c7b6722500f4055c8204a2f9345c9",
      "changed": false,
      "missing_markers": [],
      "date_mentions": [],
      "error": ""
    },
    {
      "source_id": "kaggle-sports",
      "status": "auth_required",
      "checked_at": "2026-07-14T12:04:12.374623Z",
      "url": "https://www.kaggle.com/api/v1/competitions/list?search=sports",
      "final_url": "",
      "http_status": null,
      "content_sha256": "",
      "changed": false,
      "missing_markers": [],
      "date_mentions": [],
      "error": "KAGGLE_USERNAME and KAGGLE_KEY are not configured"
    }
  ]
}
